<?xml version="1.0" encoding="UTF-8"?>
<moon_phases>
    <phase name="LUA NOVA">
        <date>2025-01-29</date>
        <date>2025-02-27</date>
        <date>2025-03-29</date>
        <date>2025-04-27</date>
        <date>2025-05-27</date>
        <date>2025-06-25</date>
        <date>2025-07-24</date>
        <date>2025-08-23</date>
        <date>2025-09-21</date>
        <date>2025-10-21</date>
        <date>2025-11-20</date>
        <date>2025-12-19</date>
    </phase>
    <phase name="LUA CRESCENTE">
        <date>2025-01-06</date>
        <date>2025-02-05</date>
        <date>2025-03-06</date>
        <date>2025-04-06</date>
        <date>2025-05-04</date>
        <date>2025-06-04</date>
        <date>2025-07-03</date>
        <date>2025-08-01</date>
        <date>2025-08-31</date>
        <date>2025-09-29</date>
        <date>2025-10-29</date>
        <date>2025-11-28</date>
        <date>2025-12-27</date>
    </phase>
    <phase name="LUA CHEIA">
        <date>2025-01-13</date>
        <date>2025-02-12</date>
        <date>2025-03-12</date>
        <date>2025-04-13</date>
        <date>2025-05-12</date>
        <date>2025-06-11</date>
        <date>2025-07-10</date>
        <date>2025-08-09</date>
        <date>2025-09-07</date>
        <date>2025-10-07</date>
        <date>2025-11-05</date>
        <date>2025-12-04</date>
    </phase>
    <phase name="LUA MINGUANTE">
        <date>2025-01-21</date>
        <date>2025-02-20</date>
        <date>2025-03-21</date>
        <date>2025-04-20</date>
        <date>2025-05-20</date>
        <date>2025-06-18</date>
        <date>2025-07-17</date>
        <date>2025-08-16</date>
        <date>2025-09-14</date>
        <date>2025-10-13</date>
        <date>2025-11-12</date>
	<date>2025-12-11</date>
    </phase>
</moon_phases>
